pyjallib/__init__.py
pyjallib/exceptions.py
pyjallib/logger.py
pyjallib/namePart.py
pyjallib/nameToPath.py
pyjallib/naming.py
pyjallib/namingConfig.py
pyjallib/perforce.py
pyjallib/progressEvent.py
pyjallib/py.typed
pyjallib/reloadModules.py
pyjallib/ConfigFiles/namingConfig.json
pyjallib/max/__init__.py
pyjallib/max/align.py
pyjallib/max/anim.py
pyjallib/max/autoClavicle.py
pyjallib/max/bip.py
pyjallib/max/bone.py
pyjallib/max/boneChain.py
pyjallib/max/constraint.py
pyjallib/max/elbow.py
pyjallib/max/fbxHandler.py
pyjallib/max/groinBone.py
pyjallib/max/header.py
pyjallib/max/helper.py
pyjallib/max/hip.py
pyjallib/max/inguinal.py
pyjallib/max/kneeBone.py
pyjallib/max/layer.py
pyjallib/max/link.py
pyjallib/max/mirror.py
pyjallib/max/mocap.py
pyjallib/max/morph.py
pyjallib/max/name.py
pyjallib/max/progress.py
pyjallib/max/rootMotion.py
pyjallib/max/select.py
pyjallib/max/shoulder.py
pyjallib/max/skeleton.py
pyjallib/max/skin.py
pyjallib/max/toolManager.py
pyjallib/max/twistBone.py
pyjallib/max/volumeBone.py
pyjallib/max/wrist.py
pyjallib/max/ConfigFiles/3DSMaxNamingConfig.json
pyjallib/max/ConfigFiles/Default_3DSMaxNamingConfig.json
pyjallib/max/macro/jal_macro_align.py
pyjallib/max/macro/jal_macro_bone.py
pyjallib/max/macro/jal_macro_constraint.py
pyjallib/max/macro/jal_macro_helper.py
pyjallib/max/macro/jal_macro_link.py
pyjallib/max/macro/jal_macro_select.py
pyjallib/max/ui/Container.py
pyjallib/max/ui/__init__.py
pyjallib/ue5/__init__.py
pyjallib/ue5/disableInterchangeFrameWork.py
pyjallib/ue5/logger.py
pyjallib/ue5/templateProcessor.py
pyjallib/ue5/ConfigFiles/UE5NamingConfig.json
pyjallib/ue5/inUnreal/__init__.py
pyjallib/ue5/inUnreal/animationImporter.py
pyjallib/ue5/inUnreal/baseImporter.py
pyjallib/ue5/inUnreal/importerSettings.py
pyjallib/ue5/inUnreal/skeletalMeshImporter.py
pyjallib/ue5/inUnreal/skeletonImporter.py
pyjallib/ue5/templates/__init__.py
pyjallib/ue5/templates/animImportTemplate.py
pyjallib/ue5/templates/batchAnimImportTemplate.py
pyjallib-0.1.20.dist-info/METADATA
pyjallib-0.1.20.dist-info/WHEEL
pyjallib-0.1.20.dist-info/RECORD
