Metadata-Version: 2.4
Name: pyjallib
Version: 0.1.20
Summary: A utility library for 3D game character development pipelines.
Author-email: Dongseok Kim <jalnagakds@gmail.com>
Requires-Python: >=3.10
Requires-Dist: p4python>=2024.2.2682690
